setup.py
coinu/__init__.py
coinu.egg-info/PKG-INFO
coinu.egg-info/SOURCES.txt
coinu.egg-info/dependency_links.txt
coinu.egg-info/top_level.txt