Metadata-Version: 1.0
Name: coinu
Version: 0.0.0.dev1
Summary: COIN Utility basic package
Home-page: https://github.com/coinu
Author: gokoro
Author-email: UNKNOWN
License: MIT
Platform: UNKNOWN
